ai_hydra/__init__.py
ai_hydra/budget_controller.py
ai_hydra/cli.py
ai_hydra/config.py
ai_hydra/error_handler.py
ai_hydra/exploration_clone.py
ai_hydra/feature_extractor.py
ai_hydra/game_logic.py
ai_hydra/headless_server.py
ai_hydra/hydra_mgr.py
ai_hydra/logging_config.py
ai_hydra/master_game.py
ai_hydra/models.py
ai_hydra/mq_client.py
ai_hydra/neural_network.py
ai_hydra/oracle_trainer.py
ai_hydra/router.py
ai_hydra/router_constants.py
ai_hydra/simple_client.py
ai_hydra/simulation_pipeline.py
ai_hydra/state_manager.py
ai_hydra/token_tracker/__init__.py
ai_hydra/token_tracker/backup_manager.py
ai_hydra/token_tracker/csv_writer.py
ai_hydra/token_tracker/error_handler.py
ai_hydra/token_tracker/hook.py
ai_hydra/token_tracker/maintenance.py
ai_hydra/token_tracker/metadata_collector.py
ai_hydra/token_tracker/models.py
ai_hydra/token_tracker/monitoring.py
ai_hydra/token_tracker/tracker.py
ai_hydra/tui/README.md
ai_hydra/tui/__init__.py
ai_hydra/tui/client.py
ai_hydra/tui/game_board.py
ai_hydra/tui/hydra_client.tcss
ai_hydra/zmq_client_example.py
ai_hydra/zmq_protocol.py
ai_hydra/zmq_server.py
ai_hydra-0.8.0.dist-info/METADATA
ai_hydra-0.8.0.dist-info/WHEEL
ai_hydra-0.8.0.dist-info/entry_points.txt
ai_hydra-0.8.0.dist-info/licenses/LICENSE
ai_hydra-0.8.0.dist-info/RECORD
