Metadata-Version: 2.4
Name: ai-hydra
Version: 0.8.0
Summary: A sophisticated parallel neural network exploration system for Snake Game AI with budget-constrained tree search
License: GPL-3.0
License-File: LICENSE
Keywords: AI,Neural Networks,Tree Search,PyTorch,Snake Game,Parallel Processing,Budget-Constrained Search,Reinforcement Learning,ZeroMQ,Hydra Zen
Author: Nadim-Daniel Ghaznavi
Author-email: nghaznavi@gmail.com
Requires-Python: >=3.11,<3.15
Classifier: Development Status :: 4 - Beta
Classifier: Intended Audience :: Developers
Classifier: Intended Audience :: Science/Research
Classifier: Programming Language :: Python :: 3
Classifier: Programming Language :: Python :: 3.11
Classifier: Programming Language :: Python :: 3.12
Classifier: License :: OSI Approved :: GNU General Public License v3 (GPLv3)
Classifier: Operating System :: OS Independent
Classifier: Topic :: Games/Entertainment :: Puzzle Games
Classifier: Topic :: Scientific/Engineering :: Artificial Intelligence
Classifier: Topic :: Software Development :: Libraries :: Python Modules
Provides-Extra: dev
Provides-Extra: docs
Provides-Extra: server
Provides-Extra: tui
Provides-Extra: viz
Requires-Dist: aiohttp (>=3.8.0) ; extra == "server"
Requires-Dist: black (>=23.0.0) ; extra == "dev"
Requires-Dist: flake8 (>=6.0.0) ; extra == "dev"
Requires-Dist: hydra-core (>=1.3.0)
Requires-Dist: hydra-zen (>=0.11.0)
Requires-Dist: hypothesis (>=6.0.0)
Requires-Dist: hypothesis (>=6.0.0) ; extra == "dev"
Requires-Dist: isort (>=5.12.0) ; extra == "dev"
Requires-Dist: matplotlib (>=3.7.0) ; extra == "viz"
Requires-Dist: mypy (>=1.0.0) ; extra == "dev"
Requires-Dist: myst-parser (>=2.0.0) ; extra == "docs"
Requires-Dist: numpy (>=1.24.0)
Requires-Dist: omegaconf (>=2.3.0)
Requires-Dist: pillow (>=10.0.0) ; extra == "viz"
Requires-Dist: psutil (>=5.9.0)
Requires-Dist: pytest (>=7.0.0)
Requires-Dist: pytest (>=7.0.0) ; extra == "dev"
Requires-Dist: pytest-asyncio (>=0.21.0) ; extra == "dev"
Requires-Dist: pytest-cov (>=4.0.0) ; extra == "dev"
Requires-Dist: pytest-mock (>=3.15.0) ; extra == "dev"
Requires-Dist: pytest-timeout (>=2.1.0) ; extra == "dev"
Requires-Dist: python-daemon (>=3.0.0) ; extra == "server"
Requires-Dist: pyyaml (>=6.0)
Requires-Dist: pyzmq (>=25.0.0)
Requires-Dist: rich (>=13.0.0) ; extra == "tui"
Requires-Dist: sphinx (>=7.0.0) ; extra == "docs"
Requires-Dist: sphinx-rtd-theme (>=1.3.0) ; extra == "docs"
Requires-Dist: tensorboard (>=2.13.0) ; extra == "viz"
Requires-Dist: textual (>=0.41.0) ; extra == "tui"
Requires-Dist: torch (>=2.0.0)
Project-URL: Bug Tracker, https://github.com/NadimGhaznavi/ai-hydra/issues
Project-URL: Documentation, https://aihydra.osoyalce.com/
Project-URL: Source, https://github.com/NadimGhaznavi/ai-hydra
